[
  {
    "id": "1",
    "tabTitle": "物资条码信息查询",
    "fragmentTag": "xinangd_material_info_qeury_fragment_tag",
    "bizType": "1000",
    "refType": "0",
    "mode": 0,
    "fragmentType": 0,
    "className": "com.richfit.barcodesystemproduct.module_infoquery.material_infoquery.MaterialInfoQueryFragment"
  },
  {
    "id": "2",
    "tabTitle": "抬头",
    "fragmentTag": "xinangd_lq_qeury_fragment_tag",
    "bizType": "2000",
    "refType": "0",
    "mode": 0,
    "fragmentType": 0,
    "className": "com.richfit.barcodesystemproduct.module_infoquery.material_liaoqian.header.LQHeaderFragment"
  },
  {
    "id": "3",
    "tabTitle": "库存明细",
    "fragmentTag": "xinangd_lq_qeury_fragment_tag",
    "bizType": "2000",
    "refType": "0",
    "mode": 0,
    "fragmentType": 0,
    "className": "com.richfit.barcodesystemproduct.module_infoquery.material_liaoqian.detail.LQDetailFragment"
  },
  {
    "id": "4",
    "tabTitle": "抬头",
    "fragmentTag": "xinangd_la_header_fragment_tag",
    "bizType": "100",
    "refType": "4",
    "mode": 0,
    "fragmentType": 1,
    "className": "com.richfit.barcodesystemproduct.module_locationadjust.header.LAHeaderFragment"
  },
  {
    "id": "5",
    "tabTitle": "数据采集",
    "fragmentTag": "xinangd_la_collect_fragment_tag",
    "bizType": "100",
    "mode": 0,
    "refType": "4",
    "fragmentType": 2,
    "className": "com.richfit.barcodesystemproduct.module_locationadjust.collect.LACollectFragment"
  }
]
